morecsv/__init__.py
morecsv/morecsv.py
morecsv-1.0.0.dist-info/licenses/LICENSE
morecsv-1.0.0.dist-info/METADATA
morecsv-1.0.0.dist-info/WHEEL
morecsv-1.0.0.dist-info/top_level.txt
morecsv-1.0.0.dist-info/RECORD
