Metadata-Version: 2.4
Name: morecsv
Version: 1.0.0
Summary: An enhanced CSV processing library with more features
Home-page: https://github.com/Unknownuserfrommars/morecsv
Author: Unknownuserfrommars
Author-email: unknownuserfrommars@protonmail.com
Classifier: Programming Language :: Python :: 3
Classifier: License :: OSI Approved :: MIT License
Classifier: Operating System :: OS Independent
Requires-Python: >=3.10
License-File: LICENSE
Requires-Dist: pandas
Requires-Dist: numpy
Requires-Dist: matplotlib
Requires-Dist: plotly
Dynamic: author
Dynamic: author-email
Dynamic: classifier
Dynamic: description
Dynamic: description-content-type
Dynamic: home-page
Dynamic: license-file
Dynamic: requires-dist
Dynamic: requires-python
Dynamic: summary
